{
    "bounds": "[363,2226][447,2269]",
    "checkable": false,
    "checked": false,
    "class": "android.view.ViewGroup",
    "clickable": false,
    "enabled": true,
    "focusable": false,
    "focused": false,
    "hash": "YnjiX2mW5JXVYDLIdoKtEQ==\n",
    "height": 43,
    "hier_level": 28,
    "human_hash": "android.view.ViewGroup_X363_Y2226_W84_H43",
    "index": "2",
    "is_transformed": true,
    "long-clickable": false,
    "password": false,
    "scrollable": false,
    "selected": false,
    "tag_name": "android.view.ViewGroup",
    "text": "CART",
    "width": 84,
    "x": 363,
    "y": 2226
}