{
    "bounds": "[556,301][1056,884]",
    "checkable": false,
    "checked": false,
    "class": "android.view.ViewGroup",
    "clickable": true,
    "content-desc": "grid-0-container-item-1",
    "enabled": true,
    "focusable": true,
    "focused": false,
    "hash": "8UnweHCZk8iFopS5tsxrHw==\n",
    "height": 583,
    "hier_level": 36,
    "human_hash": "android.view.ViewGroup_X556_Y301_W500_H583",
    "human_readable": "android.view.ViewGroup_556_301_500_583_android.view.ViewGroup_ffffffffffffffffffffbfff8fff0fff9fff03ff61ffc0ffc27f073fcf079f07_4cfd213d82c3360d355f819a111d11d0",
    "image_path": "MDA1NDFkZGE2MDY0YWI0MzIwNjQ0OWYyNTBhOTllODM.png",
    "index": "1",
    "is_transformed": true,
    "long-clickable": false,
    "password": false,
    "screen_hash": "363eac1bae2ad6462ae478c7421f5da0",
    "scrollable": false,
    "selected": false,
    "tag_name": "android.view.ViewGroup",
    "text": "Men",
    "width": 500,
    "x": 556,
    "y": 301
}