{
    "bounds": "[993,163][1037,207]",
    "checkable": false,
    "checked": false,
    "class": "android.view.ViewGroup",
    "clickable": false,
    "enabled": true,
    "focusable": false,
    "focused": false,
    "hash": "Wk8bF20GsowrvwUFxDwrbA==\n",
    "height": 44,
    "hier_level": 18,
    "human_hash": "android.view.ViewGroup_X993_Y163_W44_H44",
    "human_readable": "android.view.ViewGroup_993_163_44_44_android.view.ViewGroup_fc3ff00fe007c00381c183e106600620062006208661836101c30007f00ff83f_f4ea5f46dd32b666be3f802dfe2982c2",
    "image_path": "YjljMWU3ZTQ2Yjg5ZDVkZDNlZGFhNjhhMTViMmFmNWE.png",
    "index": "1",
    "is_transformed": true,
    "long-clickable": false,
    "password": false,
    "screen_hash": "b53b1f8a90596f40bdd1f3e2f31ea300",
    "scrollable": false,
    "selected": false,
    "tag_name": "android.view.ViewGroup",
    "text": "0",
    "width": 44,
    "x": 993,
    "y": 163
}