{
    "bounds": "[33,1692][276,1760]",
    "checkable": false,
    "checked": false,
    "class": "android.widget.TextView",
    "clickable": false,
    "enabled": true,
    "focusable": false,
    "focused": false,
    "hash": "zGVRuhsDa6KQDUn8R2B9qw==\n",
    "height": 68,
    "hier_level": 32,
    "human_hash": "android.widget.TextView_X33_Y1692_W243_H68",
    "human_readable": "android.widget.TextView_33_1692_243_68_android.widget.TextView_ffffffffffffffffbfff3dcf7dcf400841004000402800080008ffffffffffff_eeb78829aac0487e8115fb76590b9969",
    "image_path": "YTQxODk5YzMzN2NkNmVlMDAxNWFiOWUwZWE0YWRkZDA.png",
    "index": "0",
    "is_transformed": true,
    "long-clickable": false,
    "password": false,
    "screen_hash": "b53b1f8a90596f40bdd1f3e2f31ea300",
    "scrollable": false,
    "selected": false,
    "tag_name": "android.widget.TextView",
    "text": "Contact us",
    "width": 243,
    "x": 33,
    "y": 1692
}