{
    "bounds": "[960,73][1015,129]",
    "checkable": false,
    "checked": false,
    "class": "android.widget.TextView",
    "clickable": false,
    "enabled": true,
    "focusable": false,
    "focused": false,
    "hash": "wJkB0kZHf1EBeqkloWM7Jw==\n",
    "height": 56,
    "hier_level": 18,
    "human_hash": "android.widget.TextView_X960_Y73_W55_H56",
    "human_readable": "android.widget.TextView_960_73_55_56_android.widget.TextView_fffffffffffffffffffffffffff8ffe0ffc0ffc0ffc0ff800f8007c0e7c0e000_9d4568c009d203ab10e33ea9953a0264",
    "image_path": "ZmY5MTBlMWMxY2MwZWNiNGM4NTY3MGY3ODc5Mzg4M2U.png",
    "index": "0",
    "is_transformed": true,
    "long-clickable": false,
    "password": false,
    "screen_hash": "0710ab73a28b021242da36d6afaea97a",
    "scrollable": false,
    "selected": false,
    "tag_name": "android.widget.TextView",
    "text": "",
    "width": 55,
    "x": 960,
    "y": 73
}