{
    "behavior": "",
    "checkable": false,
    "class": "input",
    "clickable": true,
    "content-desc": "",
    "enabled": true,
    "focusable": true,
    "focused": false,
    "hash": "xc1V6UFkY8vDtsb3CNEv6Q==\n",
    "height": 42,
    "hier_level": 0,
    "human_hash": "input_X394_Y784_W1132_H42",
    "index": -1,
    "internal": {
        "elem_dict": {
            "attributes": {
                "autocomplete": "current-password",
                "class": "woocommerce-Input woocommerce-Input--text input-text",
                "id": "password",
                "name": "password",
                "type": "password"
            },
            "backend_node_id": 2033,
            "flags": {
                "checkable": false,
                "clickable": true,
                "enabled": true,
                "focusable": true,
                "focused": false,
                "scrollable": false
            },
            "height": 42.0,
            "key": "394_784_1132_42_",
            "tagName": "input",
            "text": "",
            "width": 1132.0,
            "x": 394.0,
            "y": 784.0
        },
        "location": {
            "x": 394.0,
            "y": 784.0
        },
        "size": {
            "height": 42.0,
            "width": 1132.0
        },
        "tag_name": "input",
        "text": ""
    },
    "is_transformed": true,
    "package": "",
    "password": false,
    "resource-id": "",
    "scrollable": false,
    "tag_name": "input",
    "text": "",
    "transformed": true,
    "width": 1132,
    "x": 394,
    "y": 784
}