{
    "bounds": "[0,2143][270,2148]",
    "checkable": false,
    "checked": false,
    "class": "android.view.ViewGroup",
    "clickable": false,
    "enabled": true,
    "focusable": false,
    "focused": false,
    "hash": "ZsCYNmgGaHrreaSUez4kcg==\n",
    "height": 5,
    "hier_level": 24,
    "human_hash": "android.view.ViewGroup_X0_Y2143_W270_H5",
    "index": "0",
    "is_transformed": true,
    "long-clickable": false,
    "password": false,
    "scrollable": false,
    "selected": false,
    "tag_name": "android.view.ViewGroup",
    "text": "",
    "width": 270,
    "x": 0,
    "y": 2143
}