{
    "bounds": "[17,408][1064,1091]",
    "checkable": false,
    "checked": false,
    "class": "android.view.ViewGroup",
    "clickable": false,
    "enabled": true,
    "focusable": false,
    "focused": false,
    "hash": "7sy0/783cPlsJ3AVZRijww==\n",
    "height": 683,
    "hier_level": 25,
    "human_hash": "android.view.ViewGroup_X17_Y408_W1047_H683",
    "index": "0",
    "is_transformed": true,
    "long-clickable": false,
    "password": false,
    "scrollable": false,
    "selected": false,
    "tag_name": "android.view.ViewGroup",
    "text": "Anchor Bracelet $100.00 Black Over-the-shoulder Handbag $150.00",
    "width": 1047,
    "x": 17,
    "y": 408
}