{
    "bounds": "[44,737][1036,804]",
    "checkable": false,
    "checked": false,
    "class": "android.widget.LinearLayout",
    "clickable": false,
    "enabled": true,
    "focusable": false,
    "focused": false,
    "hash": "7BnqOUdnOmZPZb5DJxgUUw==\n",
    "height": 67,
    "hier_level": 8,
    "human_hash": "android.widget.LinearLayout_X44_Y737_W992_H67",
    "index": "0",
    "is_transformed": true,
    "long-clickable": false,
    "password": false,
    "resource-id": "com.android.systemui:id/row",
    "scrollable": false,
    "selected": false,
    "tag_name": "android.widget.LinearLayout",
    "text": "Mon, Feb 14 44F",
    "width": 992,
    "x": 44,
    "y": 737
}