{
    "bounds": "[46,1738][107,1826]",
    "checkable": false,
    "checked": false,
    "class": "android.widget.ImageView",
    "clickable": false,
    "content-desc": "Gmail notification: Google",
    "enabled": true,
    "focusable": false,
    "focused": false,
    "hash": "OFtiEhaHKvlkvKmE1alBMQ==\n",
    "height": 88,
    "hier_level": 8,
    "human_hash": "android.widget.ImageView_X46_Y1738_W61_H88",
    "index": "0",
    "is_transformed": true,
    "long-clickable": false,
    "password": false,
    "scrollable": false,
    "selected": false,
    "tag_name": "android.widget.ImageView",
    "text": "",
    "width": 61,
    "x": 46,
    "y": 1738
}