{
    "behavior": "",
    "checkable": false,
    "class": "li",
    "clickable": true,
    "content-desc": "",
    "enabled": true,
    "focusable": true,
    "focused": false,
    "hash": "8eSaxa3m48QgVPWS0GCD2g==\n",
    "height": 112,
    "hier_level": 0,
    "human_hash": "li_X360_Y578_W239_H112",
    "human_readable": "li_360_578_239_112_li_fffffffff801f8016fff69ff08ff0fff0fbf083f083f6ffff87ff87fffffffff_94eaffa6a109ecadc85e853c7be26958",
    "image_path": "ZjU0OTQ5ODliYzc3MmJhMjBkMWQ4ZjhhMmE1NDcwY2U.png",
    "index": -1,
    "internal": {
        "elem_dict": {
            "attributes": {},
            "backend_node_id": 4389,
            "flags": {
                "checkable": false,
                "clickable": true,
                "enabled": true,
                "focusable": true,
                "focused": false,
                "scrollable": false
            },
            "height": 112.0,
            "key": "360_578_239_112_Bright Gold Purse With Chain Rated  0  out of 5 $ 250.00",
            "tagName": "li",
            "text": "Bright Gold Purse With Chain Rated  0  out of 5 $ 250.00",
            "width": 239.0,
            "x": 360.0,
            "y": 578.0
        },
        "location": {
            "x": 360.0,
            "y": 578.0
        },
        "size": {
            "height": 112.0,
            "width": 239.0
        },
        "tag_name": "li",
        "text": "Bright Gold Purse With Chain Rated  0  out of 5 $ 250.00"
    },
    "is_transformed": true,
    "package": "",
    "password": false,
    "resource-id": "",
    "screen_hash": "bd8cad5817f82cf12579862d4dd775ae",
    "scrollable": false,
    "tag_name": "li",
    "text": "Bright Gold Purse With Chain Rated  0  out of 5 $ 250.00",
    "transformed": true,
    "width": 239,
    "x": 360,
    "y": 578
}